{
  "is_token_endpoint_ip_header_trusted": false,
  "name": "DAE",
  "is_first_party": true,
  "oidc_conformant": true,
  "sso_disabled": false,
  "cross_origin_auth": false,
  "allowed_clients": [],
  "callbacks": [
    "https://drew-auth0-new.us8.webtask.io/auth0-delegated-admin/login"
  ],
  "jwt_configuration": {
    "alg": "RS256",
    "lifetime_in_seconds": 36000,
    "secret_encoded": false
  },
  "client_aliases": [],
  "token_endpoint_auth_method": "none",
  "app_type": "spa",
  "grant_types": [
    "authorization_code",
    "implicit",
    "refresh_token"
  ],
  "custom_login_page_on": true
}